metbit/STOCSY.py
metbit/__init__.py
metbit/annotate_peak.py
metbit/base.py
metbit/baseline.py
metbit/boxplot.py
metbit/calibrate.py
metbit/cross_validation.py
metbit/denoise_spec.py
metbit/dev.py
metbit/genpage.py
metbit/lazy_opls_da.py
metbit/metbit.py
metbit/nmr_preprocess.py
metbit/opls.py
metbit/pca_ellipse.py
metbit/peak_processe.py
metbit/plotting.py
metbit/pls.py
metbit/pretreatment.py
metbit/scaler.py
metbit/spec_norm.py
metbit/take_intensity.py
metbit/ui_picky_peak.py
metbit/ui_stocsy.py
metbit/utility.py
metbit/vip.py
metbit-8.7.5.dist-info/licenses/LICENSE
metbit-8.7.5.dist-info/METADATA
metbit-8.7.5.dist-info/WHEEL
metbit-8.7.5.dist-info/top_level.txt
metbit-8.7.5.dist-info/RECORD
