Metadata-Version: 2.4
Name: metbit
Version: 8.7.5
Summary: Metabolomics data analysis and visualization tools.
Home-page: https://github.com/aeiwz/metbit.git
Download-URL: https://github.com/aeiwz/metbit/archive/refs/tags/V8.7.5.tar.gz
Author: aeiwz
Author-email: theerayut_aeiw_123@hotmail.com
License: MIT
Keywords: Omics,Multivariate analysis,Visualization,Data Analysis,Metabolomics,Chemometrics
Classifier: Development Status :: 3 - Alpha
Classifier: Intended Audience :: Education
Classifier: Topic :: Software Development :: Build Tools
Classifier: License :: OSI Approved :: MIT License
Classifier: Programming Language :: Python :: 3.12
License-File: LICENSE
Requires-Dist: scikit-learn
Requires-Dist: pandas
Requires-Dist: numpy
Requires-Dist: matplotlib
Requires-Dist: seaborn
Requires-Dist: scipy==1.14.1
Requires-Dist: statsmodels
Requires-Dist: plotly
Requires-Dist: pyChemometrics
Requires-Dist: lingress
Requires-Dist: tqdm
Requires-Dist: dash
Requires-Dist: pingouin
Requires-Dist: nmrglue
Requires-Dist: pybaselines
Dynamic: author
Dynamic: author-email
Dynamic: classifier
Dynamic: download-url
Dynamic: home-page
Dynamic: keywords
Dynamic: license
Dynamic: license-file
Dynamic: requires-dist
Dynamic: summary
